LICENSE .txt
setup.py
custom_sum.egg-info/PKG-INFO
custom_sum.egg-info/SOURCES.txt
custom_sum.egg-info/dependency_links.txt
custom_sum.egg-info/top_level.txt
custome_sum/__init__.py